{
  "users": {
    "demo": {
      "points": 0,
      "pendingRewards": 0,
      "subscription": false,
      "history": []
    },
    "Kimutai": {
      "username": "Kimutai",
      "password": "Aron",
      "points": 0,
      "pendingRewards": 0,
      "subscription": false,
      "history": []
    },
    "Kiptai": {
      "username": "Kiptai",
      "password": "kiptai",
      "points": 0,
      "pendingRewards": 2050,
      "subscription": true,
      "history": [
        {
          "date": "7/14/2026, 3:36:37 AM",
          "prize": 50
        },
        {
          "date": "7/14/2026, 3:36:37 AM",
          "prize": 2000
        }
      ]
    },
    "kiptai'S": {
      "username": "kiptai'S",
      "password": "1234",
      "points": 0,
      "pendingRewards": 0,
      "subscription": false,
      "history": []
    },
    "Sheila": {
      "username": "Sheila",
      "password": "1234",
      "points": 0,
      "pendingRewards": 0,
      "subscription": false,
      "history": []
    },
    "Kemboi12": {
      "username": "Kemboi12",
      "password": "kemboi",
      "points": 0,
      "pendingRewards": 0,
      "subscription": false,
      "history": []
    }
  }
}